requestify/1.py
requestify/__init__.py
requestify/test.py
requestify-1.1.0.dist-info/DESCRIPTION.rst
requestify-1.1.0.dist-info/METADATA
requestify-1.1.0.dist-info/RECORD
requestify-1.1.0.dist-info/WHEEL
requestify-1.1.0.dist-info/metadata.json
requestify-1.1.0.dist-info/top_level.txt
