Metadata-Version: 2.0
Name: requestify
Version: 1.1.0
Summary: convert curl to python requests code
Home-page: https://github.com/minatsuki-yui/requestify
Author: Yue Minatsuki
Author-email: yue.official.jp@gmail.com
License: MIT Licence
Platform: UNKNOWN
Classifier: Development Status :: 4 - Beta
Classifier: Intended Audience :: Developers
Classifier: Programming Language :: Python :: 3.6
Requires-Python: >=3.6
Requires-Dist: requests
